cursofiap/__init__.py
cursofiap/core.py
cursofiap_packpage-1.0.1.dist-info/METADATA
cursofiap_packpage-1.0.1.dist-info/WHEEL
cursofiap_packpage-1.0.1.dist-info/top_level.txt
cursofiap_packpage-1.0.1.dist-info/RECORD
